{"pe_name":"FileSync.LocalizedResources.dll.mui","pe_type":267,"pe_size":215400,"pe_subsystem":2,"pe_subsystem_caption":"The Windows graphical user interface (GUI) subsystem","pe_path":"c:\\Users\\cyballistic\\AppData\\Local\\Microsoft\\OneDrive\\19.232.1124.0012\\sl\\FileSync.LocalizedResources.dll.mui","pe_timedate_stamp":0,"pe_timedate_human":"1970-01-01T00:00:00.000Z","ImageDLLImports":[{"name":"","imports":0,"functions":[]}],"ImageDLLExports":{"exports":0,"functions":[]},"ImageHashSignatures":{"md5":"375bd238f8e18dc0b078266cccb81ae6","sha2":"b5624b001dcf0d6aeeb24b113aaccff3fd25fad43fd9893e9387dc1e04e7f537"}}