{
  "pe_name": "lsi_sss.sys",
  "pe_type": 523,
  "pe_size": 82744,
  "pe_subsystem": 1,
  "pe_subsystem_caption": "Device drivers and native Windows processes",
  "pe_path": "c:\\Windows\\WinSxS\\amd64_dual_lsi_sss.inf_31bf3856ad364e35_10.0.19041.1_none_911d7b221df18403\\lsi_sss.sys",
  "pe_timedate_stamp": 1363390778,
  "pe_timedate_human": "2013-03-15T23:39:38.000Z",
  "ImageDLLImports": [
    {
      "name": "storport.dll",
      "imports": 19,
      "functions": [
        "ScsiPortNotification",
        "StorPortBusy",
        "StorPortExtendedFunction",
        "StorPortGetBusData",
        "StorPortGetDeviceBase",
        "StorPortGetLogicalUnit",
        "StorPortGetPhysicalAddress",
        "StorPortGetScatterGatherList",
        "StorPortGetUncachedExtension",
        "StorPortInitialize",
        "StorPortLogError",
        "StorPortNotification",
        "StorPortPause",
        "StorPortQuerySystemTime",
        "StorPortReady",
        "StorPortResume",
        "StorPortSetDeviceQueueDepth",
        "StorPortStallExecution",
        "StorPortSynchronizeAccess"
      ]
    }
  ],
  "ImageDLLExports": {
    "exports": 0,
    "functions": []
  },
  "ImageHashSignatures": {
    "sha2": "ffddb7ba54c999d5689152e4edacc838a769b6c479f0a0fcf294c8632f4e4c1f"
  }
}