{
  "pe_name": "PresentationFramework-SystemData.dll",
  "pe_type": 267,
  "pe_size": 17792,
  "pe_subsystem": 3,
  "pe_subsystem_caption": "The Windows character (Cosole UI) subsystem",
  "pe_path": "c:\\Windows\\WinSxS\\amd64_presentationframework-systemdata_b77a5c561934e089_4.0.15805.340_none_1ab69bc6f9f06562\\PresentationFramework-SystemData.dll",
  "pe_timedate_stamp": 1620856813,
  "pe_timedate_human": "2021-05-12T22:00:13.000Z",
  "ImageDLLImports": [
    {
      "name": "mscoree.dll",
      "imports": 1,
      "functions": [
        "_CorDllMain"
      ]
    }
  ],
  "ImageDLLExports": {
    "exports": 0,
    "functions": []
  },
  "ImageHashSignatures": {
    "sha2": "90b4f30d574ff6c19108718da8f40d59d542a5cf2b2ee90951927065d2d9bfab"
  }
}