{
  "pe_name": "usbohci.sys",
  "pe_type": 523,
  "pe_size": 30208,
  "pe_subsystem": 1,
  "pe_subsystem_caption": "Device drivers and native Windows processes",
  "pe_path": "c:\\Windows\\System32\\DriverStore\\FileRepository\\usbport.inf_amd64_254cd5ae09de6b08\\usbohci.sys",
  "pe_timedate_stamp": 3550885598,
  "pe_timedate_human": "2082-07-10T05:06:38.000Z",
  "ImageDLLImports": [
    {
      "name": "ntoskrnl.dll",
      "imports": 3,
      "functions": [
        "ExAllocatePoolWithTag",
        "ExFreePoolWithTag",
        "RtlGetVersion"
      ]
    },
    {
      "name": "hal.dll",
      "imports": 1,
      "functions": [
        "KeStallExecutionProcessor"
      ]
    },
    {
      "name": "usbport.dll",
      "imports": 1,
      "functions": [
        "USBPORT_RegisterUSBPortDriver"
      ]
    }
  ],
  "ImageDLLExports": {
    "exports": 0,
    "functions": []
  },
  "ImageHashSignatures": {
    "sha2": "8e2b1a8e3f8e1f88e73ae2a34b1726b5c5f6753bae3fab1e7cc82c53ff7ee891"
  },
  "scan": {
    "intentions": 1,
    "uniq_apis_matched": 1,
    "results": [
      {
        "intent": "Query and Discovery General Attributes From The Target System",
        "tag": "Discovery:T1082 - System Information Discovery",
        "component": "---",
        "inputs": 3,
        "matches": 1,
        "apis": [
          "RtlGetVersion"
        ]
      }
    ]
  }
}