{"pe_name":"bootuwf.dll","pe_type":267,"pe_size":27664,"pe_subsystem":16,"pe_subsystem_caption":"Windows boot application","pe_path":"c:\\Windows\\WinSxS\\x86_microsoft-windows-b..re-bootmanager-pcat_31bf3856ad364e35_10.0.18362.418_none_bd068a958c51d232\\bootuwf.dll","pe_timedate_stamp":1715670877,"pe_timedate_human":"2024-05-14T07:14:37.000Z","ImageDLLImports":[{"name":"bootlib.dll","imports":27,"functions":["BlDeviceClose","BlDeviceGetInformation","BlDeviceReadAtOffsetEx","BlDeviceSetInformation","BlFileClose","BlFileOpen","BlFileReadAtOffsetEx","BlGetApplicationEntry","BlGetBootOptionBoolean","BlMmAllocateHeap","BlMmAllocatePages","BlMmFreeHeap","BlMmFreePages","BlPdAllocateData","BlpDeviceOpen","BlpDeviceRegisterDeviceClass","BlpIoRegisterDestroyRoutine","BlpPdFreeDataList","BlpPdQueryDataList","_alldiv","_allmul","_allrem","_aulldvrm","_purecall","memcpy","memmove","memset"]}],"ImageDLLExports":{"exports":2,"functions":["UwfDestroy","UwfInitialize"]},"ImageHashSignatures":{"md5":"09270b24b513bbf6e72e619f0be9dcfe","sha2":"fdfaec903ce3c1c7682f864c32ead78c0c87545b76ff1508375f4e626b86512b"}}