{"pe_name":"esent.dll","pe_type":267,"pe_size":2875904,"pe_subsystem":3,"pe_subsystem_caption":"The Windows character (Cosole UI) subsystem","pe_path":"c:\\Windows\\WinSxS\\wow64_microsoft-windows-e..estorageengine-isam_31bf3856ad364e35_10.0.18362.693_none_51d8e7c2f2309c85\\esent.dll","pe_timedate_stamp":4020215015,"pe_timedate_human":"2097-05-24T06:23:35.000Z","ImageDLLImports":[{"name":"msvcrt.dll","imports":71,"functions":["__dllonexit","__iob_func","_amsg_exit","_except_handler4_common","_ftol2","_ftol2_sse","_initterm","_itoa_s","_lock","_onexit","_purecall","_snprintf_s","_stricmp","_strnicmp","_ultoa_s","_unlock","_vsnprintf","_vsnwprintf","_wcsicmp","_wcsnicmp","_wcstoi64","_wcstoui64","_wfopen_s","_wfullpath","_wmakepath_s","_wsplitpath_s","_wtoi64","_wtol","bsearch","fclose","fflush","fprintf","free","iscntrl","isprint","isupper","iswalpha","iswprint","malloc","memcmp","memcpy","memcpy_s","memmove","memset","modf","printf","qsort","rand","rand_s","sprintf_s","strchr","strcspn","strncmp","strpbrk","strrchr","strstr","strtok_s","strtoul","swprintf_s","swscanf_s","time","vprintf","wcschr","wcscspn","wcsncmp","wcspbrk","wcsrchr","wcsstr","wcstok_s","wcstol","wprintf"]},{"name":"ntdll.dll","imports":1,"functions":["RtlCaptureStackBackTrace"]},{"name":"api-ms-win-core-processthreads-l1-1-0.dll","imports":15,"functions":["CreateProcessW","CreateThread","GetCurrentProcess","GetCurrentProcessId","GetCurrentThread","GetCurrentThreadId","GetExitCodeThread","ResumeThread","SetThreadPriority","SetThreadPriorityBoost","TerminateProcess","TlsAlloc","TlsFree","TlsGetValue","TlsSetValue"]},{"name":"api-ms-win-core-libraryloader-l1-2-0.dll","imports":7,"functions":["DisableThreadLibraryCalls","FreeLibrary","GetModuleFileNameW","GetModuleHandleExW","GetModuleHandleW","GetProcAddress","LoadLibraryExW"]},{"name":"api-ms-win-core-heap-l1-1-0.dll","imports":5,"functions":["GetProcessHeap","HeapAlloc","HeapDestroy","HeapFree","HeapSetInformation"]},{"name":"api-ms-win-core-errorhandling-l1-1-0.dll","imports":4,"functions":["GetLastError","SetLastError","SetUnhandledExceptionFilter","UnhandledExceptionFilter"]},{"name":"api-ms-win-core-sysinfo-l1-2-0.dll","imports":1,"functions":["GetNativeSystemInfo"]},{"name":"api-ms-win-core-sysinfo-l1-1-0.dll","imports":9,"functions":["GetLocalTime","GetSystemInfo","GetSystemTime","GetSystemTimeAsFileTime","GetSystemWindowsDirectoryW","GetTickCount","GetVersionExW","GetWindowsDirectoryW","GlobalMemoryStatusEx"]},{"name":"api-ms-win-core-memory-l1-1-0.dll","imports":9,"functions":["CreateFileMappingW","MapViewOfFile","MapViewOfFileEx","OpenFileMappingW","UnmapViewOfFile","VirtualAlloc","VirtualFree","VirtualProtect","VirtualQueryEx"]},{"name":"api-ms-win-core-memory-l1-1-1.dll","imports":3,"functions":["CreateMemoryResourceNotification","QueryMemoryResourceNotification","VirtualUnlock"]},{"name":"api-ms-win-core-handle-l1-1-0.dll","imports":3,"functions":["CloseHandle","DuplicateHandle","SetHandleInformation"]},{"name":"api-ms-win-core-heap-l2-1-0.dll","imports":2,"functions":["LocalAlloc","LocalFree"]},{"name":"api-ms-win-core-file-l1-1-0.dll","imports":23,"functions":["CreateDirectoryW","CreateFileW","DeleteFileW","FindClose","FindFirstFileW","FindNextFileW","FlushFileBuffers","GetDiskFreeSpaceExW","GetDriveTypeW","GetFileAttributesExW","GetFileAttributesW","GetFileInformationByHandle","GetFileSizeEx","GetVolumePathNameW","ReadFile","ReadFileScatter","RemoveDirectoryW","SetEndOfFile","SetFileInformationByHandle","SetFilePointerEx","SetFileValidData","WriteFile","WriteFileGather"]},{"name":"api-ms-win-core-synch-l1-1-0.dll","imports":18,"functions":["AcquireSRWLockExclusive","CreateEventW","CreateMutexW","DeleteCriticalSection","EnterCriticalSection","InitializeCriticalSectionAndSpinCount","LeaveCriticalSection","OpenEventW","OpenMutexW","ReleaseMutex","ReleaseSRWLockExclusive","ReleaseSemaphore","ResetEvent","SetEvent","SleepEx","WaitForMultipleObjectsEx","WaitForSingleObject","WaitForSingleObjectEx"]},{"name":"api-ms-win-core-io-l1-1-0.dll","imports":5,"functions":["CreateIoCompletionPort","DeviceIoControl","GetOverlappedResult","GetQueuedCompletionStatus","PostQueuedCompletionStatus"]},{"name":"api-ms-win-core-string-l1-1-0.dll","imports":2,"functions":["MultiByteToWideChar","WideCharToMultiByte"]},{"name":"api-ms-win-core-debug-l1-1-0.dll","imports":2,"functions":["DebugBreak","OutputDebugStringA"]},{"name":"api-ms-win-core-localization-l1-2-0.dll","imports":6,"functions":["FormatMessageW","GetLocaleInfoEx","GetLocaleInfoW","LCMapStringEx","LCMapStringW","LocaleNameToLCID"]},{"name":"api-ms-win-core-synch-l1-2-0.dll","imports":3,"functions":["Sleep","SleepConditionVariableSRW","WakeAllConditionVariable"]},{"name":"api-ms-win-core-processthreads-l1-1-1.dll","imports":1,"functions":["IsProcessorFeaturePresent"]},{"name":"api-ms-win-core-console-l1-1-0.dll","imports":1,"functions":["SetConsoleCtrlHandler"]},{"name":"api-ms-win-core-profile-l1-1-0.dll","imports":2,"functions":["QueryPerformanceCounter","QueryPerformanceFrequency"]},{"name":"api-ms-win-core-timezone-l1-1-0.dll","imports":3,"functions":["FileTimeToSystemTime","SystemTimeToFileTime","SystemTimeToTzSpecificLocalTime"]},{"name":"api-ms-win-core-datetime-l1-1-0.dll","imports":2,"functions":["GetDateFormatW","GetTimeFormatW"]},{"name":"api-ms-win-core-file-l1-2-0.dll","imports":1,"functions":["GetVolumeNameForVolumeMountPointW"]},{"name":"api-ms-win-core-file-l2-1-0.dll","imports":2,"functions":["CopyFileExW","MoveFileExW"]},{"name":"api-ms-win-core-processenvironment-l1-1-0.dll","imports":1,"functions":["GetStdHandle"]},{"name":"api-ms-win-core-console-l2-1-0.dll","imports":1,"functions":["GetConsoleScreenBufferInfo"]},{"name":"api-ms-win-core-errorhandling-l1-1-3.dll","imports":1,"functions":["SetThreadErrorMode"]},{"name":"api-ms-win-core-localization-l1-2-2.dll","imports":1,"functions":["LCIDToLocaleName"]},{"name":"api-ms-win-eventing-provider-l1-1-0.dll","imports":3,"functions":["EventRegister","EventUnregister","EventWriteTransfer"]},{"name":"api-ms-win-core-privateprofile-l1-1-0.dll","imports":1,"functions":["GetProfileStringW"]},{"name":"api-ms-win-core-processtopology-obsolete-l1-1-0.dll","imports":1,"functions":["GetProcessAffinityMask"]},{"name":"api-ms-win-core-kernel32-legacy-l1-1-0.dll","imports":2,"functions":["GetSystemPowerStatus","RegisterWaitForSingleObject"]},{"name":"api-ms-win-core-threadpool-legacy-l1-1-0.dll","imports":5,"functions":["CreateTimerQueue","CreateTimerQueueTimer","DeleteTimerQueueEx","DeleteTimerQueueTimer","UnregisterWaitEx"]},{"name":"api-ms-win-core-windowserrorreporting-l1-1-0.dll","imports":1,"functions":["WerRegisterMemoryBlock"]},{"name":"api-ms-win-core-delayload-l1-1-1.dll","imports":1,"functions":["ResolveDelayLoadedAPI"]},{"name":"api-ms-win-core-delayload-l1-1-0.dll","imports":1,"functions":["DelayLoadFailureHook"]}],"ImageDLLExports":{"exports":665,"functions":["DebugExtensionInitialize@8","DebugExtensionNotify@12","DebugExtensionUninitialize@0","JetAddColumnA@28","JetAddColumnW@28","JetAttachDatabase2A@16","JetAttachDatabase2W@16","JetAttachDatabase3A@20","JetAttachDatabase3W@20","JetAttachDatabaseA@12","JetAttachDatabaseW@12","JetAttachDatabaseWithStreamingA@24","JetAttachDatabaseWithStreamingW@24","JetBackupA@12","JetBackupInstanceA@16","JetBackupInstanceW@16","JetBackupW@12","JetBeginDatabaseIncrementalReseedA@12","JetBeginDatabaseIncrementalReseedW@12","JetBeginExternalBackup@4","JetBeginExternalBackupInstance@8","JetBeginSessionA@16","JetBeginSessionW@16","JetBeginSurrogateBackup@16","JetBeginTransaction2@8","JetBeginTransaction3@16","JetBeginTransaction@4","JetCloseDatabase@12","JetCloseFile@4","JetCloseFileInstance@8","JetCloseTable@8","JetCommitTransaction2@16","JetCommitTransaction@8","JetCompactA@24","JetCompactW@24","JetComputeStats@8","JetConfigureProcessForCrashDump@4","JetConsumeLogData@20","JetConvertDDLA@20","JetConvertDDLW@20","JetCreateDatabase2A@20","JetCreateDatabase2W@20","JetCreateDatabase3A@24","JetCreateDatabase3W@24","JetCreateDatabaseA@20","JetCreateDatabaseW@20","JetCreateDatabaseWithStreamingA@28","JetCreateDatabaseWithStreamingW@28","JetCreateEncryptionKey@16","JetCreateIndex2A@16","JetCreateIndex2W@16","JetCreateIndexA@28","JetCreateIndexW@28","JetCreateInstance2A@16","JetCreateInstance2W@16","JetCreateInstanceA@8","JetCreateInstanceW@8","JetCreateTableA@24","JetCreateTableColumnIndex2A@12","JetCreateTableColumnIndex2W@12","JetCreateTableColumnIndex3A@12","JetCreateTableColumnIndex3W@12","JetCreateTableColumnIndex4A@12","JetCreateTableColumnIndex4W@12","JetCreateTableColumnIndex5A@12","JetCreateTableColumnIndex5W@12","JetCreateTableColumnIndexA@12","JetCreateTableColumnIndexW@12","JetCreateTableW@24","JetDBUtilitiesA@4","JetDBUtilitiesW@4","JetDatabaseScan@24","JetDefragment2A@28","JetDefragment2W@28","JetDefragment3A@32","JetDefragment3W@32","JetDefragmentA@24","JetDefragmentW@24","JetDelete@8","JetDeleteColumn2A@16","JetDeleteColumn2W@16","JetDeleteColumnA@12","JetDeleteColumnW@12","JetDeleteIndexA@12","JetDeleteIndexW@12","JetDeleteTableA@12","JetDeleteTableW@12","JetDetachDatabase2A@12","JetDetachDatabase2W@12","JetDetachDatabaseA@8","JetDetachDatabaseW@8","JetDupCursor@16","JetDupSession@8","JetEnableMultiInstanceA@12","JetEnableMultiInstanceW@12","JetEndDatabaseIncrementalReseedA@24","JetEndDatabaseIncrementalReseedW@24","JetEndExternalBackup@0","JetEndExternalBackupInstance2@8","JetEndExternalBackupInstance@4","JetEndSession@8","JetEndSurrogateBackup@8","JetEnumerateColumns@40","JetEscrowUpdate@36","JetExternalRestore2A@40","JetExternalRestore2W@40","JetExternalRestoreA@32","JetExternalRestoreW@32","JetFreeBuffer@4","JetGetAttachInfoA@12","JetGetAttachInfoInstanceA@16","JetGetAttachInfoInstanceW@16","JetGetAttachInfoW@12","JetGetBookmark@20","JetGetColumnInfoA@28","JetGetColumnInfoW@28","JetGetCounter@12","JetGetCurrentIndexA@16","JetGetCurrentIndexW@16","JetGetCursorInfo@20","JetGetDatabaseFileInfoA@16","JetGetDatabaseFileInfoW@16","JetGetDatabaseInfoA@20","JetGetDatabaseInfoW@20","JetGetDatabasePages@32","JetGetErrorInfoW@20","JetGetIndexInfoA@28","JetGetIndexInfoW@28","JetGetInstanceInfoA@8","JetGetInstanceInfoW@8","JetGetInstanceMiscInfo@16","JetGetLS@16","JetGetLock@12","JetGetLogFileInfoA@16","JetGetLogFileInfoW@16","JetGetLogInfoA@12","JetGetLogInfoInstance2A@20","JetGetLogInfoInstance2W@20","JetGetLogInfoInstanceA@16","JetGetLogInfoInstanceW@16","JetGetLogInfoW@12","JetGetMaxDatabaseSize@16","JetGetObjectInfoA@32","JetGetObjectInfoW@32","JetGetPageInfo2@24","JetGetPageInfo@24","JetGetRecordPosition@16","JetGetRecordSize2@16","JetGetRecordSize@16","JetGetResourceParam@16","JetGetSecondaryIndexBookmark@36","JetGetSessionInfo@16","JetGetSessionParameter@20","JetGetSystemParameterA@24","JetGetSystemParameterW@24","JetGetTableColumnInfoA@24","JetGetTableColumnInfoW@24","JetGetTableIndexInfoA@24","JetGetTableIndexInfoW@24","JetGetTableInfoA@20","JetGetTableInfoW@20","JetGetThreadStats@8","JetGetTruncateLogInfoInstanceA@16","JetGetTruncateLogInfoInstanceW@16","JetGetVersion@8","JetGotoBookmark@16","JetGotoPosition@12","JetGotoSecondaryIndexBookmark@28","JetGrowDatabase@16","JetIdle@8","JetIndexRecordCount2@20","JetIndexRecordCount@16","JetInit2@8","JetInit3A@12","JetInit3W@12","JetInit4A@12","JetInit4W@12","JetInit@4","JetIntersectIndexes@20","JetMakeKey@20","JetMove@16","JetOSSnapshotAbort@8","JetOSSnapshotEnd@8","JetOSSnapshotFreezeA@16","JetOSSnapshotFreezeW@16","JetOSSnapshotGetFreezeInfoA@16","JetOSSnapshotGetFreezeInfoW@16","JetOSSnapshotPrepare@8","JetOSSnapshotPrepareInstance@12","JetOSSnapshotThaw@8","JetOSSnapshotTruncateLog@8","JetOSSnapshotTruncateLogInstance@12","JetOnlinePatchDatabasePage@32","JetOpenDatabaseA@20","JetOpenDatabaseW@20","JetOpenFileA@16","JetOpenFileInstanceA@20","JetOpenFileInstanceW@20","JetOpenFileSectionInstanceA@36","JetOpenFileSectionInstanceW@36","JetOpenFileW@16","JetOpenTableA@28","JetOpenTableW@28","JetOpenTempTable2@28","JetOpenTempTable3@28","JetOpenTempTable@24","JetOpenTemporaryTable2@8","JetOpenTemporaryTable@8","JetPatchDatabasePagesA@28","JetPatchDatabasePagesW@28","JetPrepareToCommitTransaction@16","JetPrepareUpdate@12","JetPrereadColumnsByReference@36","JetPrereadIndexRange@28","JetPrereadIndexRanges@32","JetPrereadKeys@28","JetPrereadTablesW@20","JetReadFile@16","JetReadFileInstance@20","JetRegisterCallback@24","JetRemoveLogfileA@12","JetRemoveLogfileW@12","JetRenameColumnA@20","JetRenameColumnW@20","JetRenameTableA@16","JetRenameTableW@16","JetResetCounter@8","JetResetSessionContext@4","JetResetTableSequential@12","JetResizeDatabase@20","JetRestore2A@12","JetRestore2W@12","JetRestoreA@8","JetRestoreInstanceA@16","JetRestoreInstanceW@16","JetRestoreW@8","JetRetrieveColumn@32","JetRetrieveColumnByReference@36","JetRetrieveColumnFromRecordStream@28","JetRetrieveColumns@16","JetRetrieveKey@24","JetRetrieveTaggedColumnList@28","JetRollback@8","JetSeek@12","JetSetColumn@28","JetSetColumnDefaultValueA@28","JetSetColumnDefaultValueW@28","JetSetColumns@16","JetSetCurrentIndex2A@16","JetSetCurrentIndex2W@16","JetSetCurrentIndex3A@20","JetSetCurrentIndex3W@20","JetSetCurrentIndex4A@24","JetSetCurrentIndex4W@24","JetSetCurrentIndexA@12","JetSetCurrentIndexW@12","JetSetCursorFilter@20","JetSetDatabaseSizeA@16","JetSetDatabaseSizeW@16","JetSetIndexRange@12","JetSetLS@16","JetSetMaxDatabaseSize@16","JetSetResourceParam@16","JetSetSessionContext@8","JetSetSessionParameter@16","JetSetSystemParameterA@20","JetSetSystemParameterW@20","JetSetTableInfoA@20","JetSetTableSequential@12","JetSnapshotStartA@12","JetSnapshotStartW@12","JetSnapshotStop@8","JetStopBackup@0","JetStopBackupInstance@4","JetStopService@0","JetStopServiceInstance2@8","JetStopServiceInstance@4","JetStreamRecords@32","JetTerm2@8","JetTerm@4","JetTestHook@8","JetTracing@12","JetTruncateLog@0","JetTruncateLogInstance@4","JetUnregisterCallback@16","JetUpdate2@24","JetUpdate@20","JetUpgradeDatabaseA@16","JetUpgradeDatabaseW@16","DebugExtensionInitialize","DebugExtensionNotify","DebugExtensionUninitialize","JetAddColumn","JetAddColumnA","JetAddColumnW","JetAttachDatabase2","JetAttachDatabase2A","JetAttachDatabase2W","JetAttachDatabase3","JetAttachDatabase3A","JetAttachDatabase3W","JetAttachDatabase","JetAttachDatabaseA","JetAttachDatabaseW","JetAttachDatabaseWithStreaming","JetAttachDatabaseWithStreamingA","JetAttachDatabaseWithStreamingW","JetBackup","JetBackupA","JetBackupInstance","JetBackupInstanceA","JetBackupInstanceW","JetBackupW","JetBeginDatabaseIncrementalReseed","JetBeginDatabaseIncrementalReseedA","JetBeginDatabaseIncrementalReseedW","JetBeginExternalBackup","JetBeginExternalBackupInstance","JetBeginSession","JetBeginSessionA","JetBeginSessionW","JetBeginSurrogateBackup","JetBeginTransaction2","JetBeginTransaction3","JetBeginTransaction","JetCloseDatabase","JetCloseFile","JetCloseFileInstance","JetCloseTable","JetCommitTransaction2","JetCommitTransaction","JetCompact","JetCompactA","JetCompactW","JetComputeStats","JetConfigureProcessForCrashDump","JetConsumeLogData","JetConvertDDL","JetConvertDDLA","JetConvertDDLW","JetCreateDatabase2","JetCreateDatabase2A","JetCreateDatabase2W","JetCreateDatabase3","JetCreateDatabase3A","JetCreateDatabase3W","JetCreateDatabase","JetCreateDatabaseA","JetCreateDatabaseW","JetCreateDatabaseWithStreaming","JetCreateDatabaseWithStreamingA","JetCreateDatabaseWithStreamingW","JetCreateEncryptionKey","JetCreateIndex2","JetCreateIndex2A","JetCreateIndex2W","JetCreateIndex3A","JetCreateIndex3W","JetCreateIndex4A","JetCreateIndex4W","JetCreateIndex","JetCreateIndexA","JetCreateIndexW","JetCreateInstance2","JetCreateInstance2A","JetCreateInstance2W","JetCreateInstance","JetCreateInstanceA","JetCreateInstanceW","JetCreateTable","JetCreateTableA","JetCreateTableColumnIndex2","JetCreateTableColumnIndex2A","JetCreateTableColumnIndex2W","JetCreateTableColumnIndex3A","JetCreateTableColumnIndex3W","JetCreateTableColumnIndex4A","JetCreateTableColumnIndex4W","JetCreateTableColumnIndex5A","JetCreateTableColumnIndex5W","JetCreateTableColumnIndex","JetCreateTableColumnIndexA","JetCreateTableColumnIndexW","JetCreateTableW","JetDBUtilities","JetDBUtilitiesA","JetDBUtilitiesW","JetDatabaseScan","JetDefragment2","JetDefragment2A","JetDefragment2W","JetDefragment3","JetDefragment3A","JetDefragment3W","JetDefragment","JetDefragmentA","JetDefragmentW","JetDelete","JetDeleteColumn2","JetDeleteColumn2A","JetDeleteColumn2W","JetDeleteColumn","JetDeleteColumnA","JetDeleteColumnW","JetDeleteIndex","JetDeleteIndexA","JetDeleteIndexW","JetDeleteTable","JetDeleteTableA","JetDeleteTableW","JetDetachDatabase2","JetDetachDatabase2A","JetDetachDatabase2W","JetDetachDatabase","JetDetachDatabaseA","JetDetachDatabaseW","JetDupCursor","JetDupSession","JetEnableMultiInstance","JetEnableMultiInstanceA","JetEnableMultiInstanceW","JetEndDatabaseIncrementalReseed","JetEndDatabaseIncrementalReseedA","JetEndDatabaseIncrementalReseedW","JetEndExternalBackup","JetEndExternalBackupInstance2","JetEndExternalBackupInstance","JetEndSession","JetEndSurrogateBackup","JetEnumerateColumns","JetEscrowUpdate","JetExternalRestore2","JetExternalRestore2A","JetExternalRestore2W","JetExternalRestore","JetExternalRestoreA","JetExternalRestoreW","JetFreeBuffer","JetGetAttachInfo","JetGetAttachInfoA","JetGetAttachInfoInstance","JetGetAttachInfoInstanceA","JetGetAttachInfoInstanceW","JetGetAttachInfoW","JetGetBookmark","JetGetColumnInfo","JetGetColumnInfoA","JetGetColumnInfoW","JetGetCounter","JetGetCurrentIndex","JetGetCurrentIndexA","JetGetCurrentIndexW","JetGetCursorInfo","JetGetDatabaseFileInfo","JetGetDatabaseFileInfoA","JetGetDatabaseFileInfoW","JetGetDatabaseInfo","JetGetDatabaseInfoA","JetGetDatabaseInfoW","JetGetDatabasePages","JetGetErrorInfoW","JetGetIndexInfo","JetGetIndexInfoA","JetGetIndexInfoW","JetGetInstanceInfo","JetGetInstanceInfoA","JetGetInstanceInfoW","JetGetInstanceMiscInfo","JetGetLS","JetGetLock","JetGetLogFileInfo","JetGetLogFileInfoA","JetGetLogFileInfoW","JetGetLogInfo","JetGetLogInfoA","JetGetLogInfoInstance2","JetGetLogInfoInstance2A","JetGetLogInfoInstance2W","JetGetLogInfoInstance","JetGetLogInfoInstanceA","JetGetLogInfoInstanceW","JetGetLogInfoW","JetGetMaxDatabaseSize","JetGetObjectInfo","JetGetObjectInfoA","JetGetObjectInfoW","JetGetPageInfo2","JetGetPageInfo","JetGetRecordPosition","JetGetRecordSize2","JetGetRecordSize","JetGetResourceParam","JetGetSecondaryIndexBookmark","JetGetSessionInfo","JetGetSessionParameter","JetGetSystemParameter","JetGetSystemParameterA","JetGetSystemParameterW","JetGetTableColumnInfo","JetGetTableColumnInfoA","JetGetTableColumnInfoW","JetGetTableIndexInfo","JetGetTableIndexInfoA","JetGetTableIndexInfoW","JetGetTableInfo","JetGetTableInfoA","JetGetTableInfoW","JetGetThreadStats","JetGetTruncateLogInfoInstance","JetGetTruncateLogInfoInstanceA","JetGetTruncateLogInfoInstanceW","JetGetVersion","JetGotoBookmark","JetGotoPosition","JetGotoSecondaryIndexBookmark","JetGrowDatabase","JetIdle","JetIndexRecordCount2","JetIndexRecordCount","JetInit2","JetInit3","JetInit3A","JetInit3W","JetInit4","JetInit4A","JetInit4W","JetInit","JetIntersectIndexes","JetMakeKey","JetMove","JetOSSnapshotAbort","JetOSSnapshotEnd","JetOSSnapshotFreeze","JetOSSnapshotFreezeA","JetOSSnapshotFreezeW","JetOSSnapshotGetFreezeInfo","JetOSSnapshotGetFreezeInfoA","JetOSSnapshotGetFreezeInfoW","JetOSSnapshotPrepare","JetOSSnapshotPrepareInstance","JetOSSnapshotThaw","JetOSSnapshotTruncateLog","JetOSSnapshotTruncateLogInstance","JetOnlinePatchDatabasePage","JetOpenDatabase","JetOpenDatabaseA","JetOpenDatabaseW","JetOpenFile","JetOpenFileA","JetOpenFileInstance","JetOpenFileInstanceA","JetOpenFileInstanceW","JetOpenFileSectionInstance","JetOpenFileSectionInstanceA","JetOpenFileSectionInstanceW","JetOpenFileW","JetOpenTable","JetOpenTableA","JetOpenTableW","JetOpenTempTable2","JetOpenTempTable3","JetOpenTempTable","JetOpenTemporaryTable2","JetOpenTemporaryTable","JetPatchDatabasePages","JetPatchDatabasePagesA","JetPatchDatabasePagesW","JetPrepareToCommitTransaction","JetPrepareUpdate","JetPrereadColumnsByReference","JetPrereadIndexRange","JetPrereadIndexRanges","JetPrereadKeys","JetPrereadTablesW","JetReadFile","JetReadFileInstance","JetRegisterCallback","JetRemoveLogfileA","JetRemoveLogfileW","JetRenameColumn","JetRenameColumnA","JetRenameColumnW","JetRenameTable","JetRenameTableA","JetRenameTableW","JetResetCounter","JetResetSessionContext","JetResetTableSequential","JetResizeDatabase","JetRestore2","JetRestore2A","JetRestore2W","JetRestore","JetRestoreA","JetRestoreInstance","JetRestoreInstanceA","JetRestoreInstanceW","JetRestoreW","JetRetrieveColumn","JetRetrieveColumnByReference","JetRetrieveColumnFromRecordStream","JetRetrieveColumns","JetRetrieveKey","JetRetrieveTaggedColumnList","JetRollback","JetSeek","JetSetColumn","JetSetColumnDefaultValue","JetSetColumnDefaultValueA","JetSetColumnDefaultValueW","JetSetColumns","JetSetCurrentIndex2","JetSetCurrentIndex2A","JetSetCurrentIndex2W","JetSetCurrentIndex3","JetSetCurrentIndex3A","JetSetCurrentIndex3W","JetSetCurrentIndex4","JetSetCurrentIndex4A","JetSetCurrentIndex4W","JetSetCurrentIndex","JetSetCurrentIndexA","JetSetCurrentIndexW","JetSetCursorFilter","JetSetDatabaseSize","JetSetDatabaseSizeA","JetSetDatabaseSizeW","JetSetIndexRange","JetSetLS","JetSetMaxDatabaseSize","JetSetResourceParam","JetSetSessionContext","JetSetSessionParameter","JetSetSystemParameter","JetSetSystemParameterA","JetSetSystemParameterW","JetSetTableInfo","JetSetTableInfoA","JetSetTableInfoW","JetSetTableSequential","JetSnapshotStart","JetSnapshotStartA","JetSnapshotStartW","JetSnapshotStop","JetStopBackup","JetStopBackupInstance","JetStopService","JetStopServiceInstance2","JetStopServiceInstance","JetStreamRecords","JetTerm2","JetTerm","JetTestHook","JetTracing","JetTruncateLog","JetTruncateLogInstance","JetUnregisterCallback","JetUpdate2","JetUpdate","JetUpgradeDatabase","JetUpgradeDatabaseA","JetUpgradeDatabaseW","ese","rgEDBGGlobals","ese@8"]},"ImageHashSignatures":{"md5":"91687dab481ccbd24902061ad18d35cb","sha2":"48143ff141fcd4ac6c8baa7aee5e70a7ed0f0108c2b13073b42f1694b0ac1e23"}}