{"pe_name":"Windows.UI.Xaml.Resources.win8rtm.dll","pe_type":523,"pe_size":142336,"pe_subsystem":3,"pe_subsystem_caption":"The Windows character (Cosole UI) subsystem","pe_path":"c:\\Windows\\WinSxS\\amd64_microsoft-windows-d..ui-resourceswin8rtm_31bf3856ad364e35_10.0.18362.1_none_5d1048a95ffeec62\\Windows.UI.Xaml.Resources.win8rtm.dll","pe_timedate_stamp":3575569643,"pe_timedate_human":"2083-04-21T21:47:23.000Z","ImageDLLImports":[{"name":"","imports":0,"functions":[]}],"ImageDLLExports":{"exports":0,"functions":[]},"ImageHashSignatures":{"md5":"83e82a30a0c51879e2b9e63fbae4469f","sha2":"b5f45a89e02bc0dff56ef5837239e19b690bc5d0fffbe9747d06ada9e6a4973a"}}