{"pe_name":"CloudNotifications.exe","pe_type":523,"pe_size":60416,"pe_subsystem":2,"pe_subsystem_caption":"The Windows graphical user interface (GUI) subsystem","pe_path":"c:\\Windows\\WinSxS\\amd64_microsoft-windows-cloudnotifications_31bf3856ad364e35_10.0.18362.752_none_e7d1d3bd22e187f8\\CloudNotifications.exe","pe_timedate_stamp":3498698914,"pe_timedate_human":"2080-11-13T04:48:34.000Z","ImageDLLImports":[{"name":"advapi32.dll","imports":3,"functions":["RegCloseKey","RegCreateKeyExW","RegSetValueExW"]},{"name":"kernel32.dll","imports":29,"functions":["CloseHandle","CreateMutexExW","CreateMutexW","CreateSemaphoreExW","DebugBreak","DelayLoadFailureHook","FindResourceExW","FormatMessageW","GetCurrentProcessId","GetCurrentThreadId","GetLastError","GetModuleFileNameA","GetModuleHandleExW","GetModuleHandleW","GetProcAddress","GetProcessHeap","HeapAlloc","HeapFree","IsDebuggerPresent","LoadResource","LockResource","OpenSemaphoreW","OutputDebugStringW","ReleaseMutex","ReleaseSemaphore","ResolveDelayLoadedAPI","SetLastError","WaitForSingleObject","WaitForSingleObjectEx"]},{"name":"user32.dll","imports":3,"functions":["DispatchMessageW","GetMessageW","TranslateMessage"]},{"name":"msvcrt.dll","imports":36,"functions":["??0exception@@QEAA@AEBQEBD@Z","??0exception@@QEAA@AEBQEBDH@Z","??0exception@@QEAA@AEBV0@@Z","??1exception@@UEAA@XZ","??1type_info@@UEAA@XZ","??3@YAXPEAX@Z","?terminate@@YAXXZ","?what@exception@@UEBAPEBDXZ","_CxxThrowException","_XcptFilter","__C_specific_handler","__CxxFrameHandler3","__dllonexit","__set_app_type","__setusermatherr","__wgetmainargs","_amsg_exit","_callnewh","_cexit","_commode","_exit","_fmode","_initterm","_lock","_onexit","_purecall","_unlock","_vsnwprintf","_wcmdln","exit","malloc","memcpy","memcpy_s","memmove","memset","wcsstr"]},{"name":"shlwapi.dll","imports":3,"functions":["PathAppendW","PathRemoveFileSpecW","SHGetThreadRef"]},{"name":"api-ms-win-core-com-l1-1-0.dll","imports":6,"functions":["CoCreateInstance","CoInitializeEx","CoTaskMemAlloc","CoTaskMemFree","CoTaskMemRealloc","CoUninitialize"]},{"name":"api-ms-win-core-winrt-error-l1-1-0.dll","imports":1,"functions":["SetRestrictedErrorInfo"]},{"name":"api-ms-win-core-winrt-error-l1-1-1.dll","imports":1,"functions":["RoGetMatchingRestrictedErrorInfo"]},{"name":"api-ms-win-core-synch-l1-2-0.dll","imports":1,"functions":["Sleep"]},{"name":"api-ms-win-core-processthreads-l1-1-0.dll","imports":7,"functions":["GetCurrentProcess","GetStartupInfoW","TerminateProcess","TlsAlloc","TlsFree","TlsGetValue","TlsSetValue"]},{"name":"api-ms-win-core-rtlsupport-l1-1-0.dll","imports":3,"functions":["RtlCaptureContext","RtlLookupFunctionEntry","RtlVirtualUnwind"]},{"name":"api-ms-win-core-errorhandling-l1-1-0.dll","imports":3,"functions":["RaiseException","SetUnhandledExceptionFilter","UnhandledExceptionFilter"]},{"name":"api-ms-win-core-profile-l1-1-0.dll","imports":1,"functions":["QueryPerformanceCounter"]},{"name":"api-ms-win-core-sysinfo-l1-1-0.dll","imports":2,"functions":["GetSystemTimeAsFileTime","GetTickCount"]},{"name":"api-ms-win-core-winrt-string-l1-1-0.dll","imports":5,"functions":["WindowsCreateString","WindowsCreateStringReference","WindowsDeleteString","WindowsGetStringRawBuffer","WindowsReplaceString"]},{"name":"api-ms-win-core-synch-l1-1-0.dll","imports":2,"functions":["AcquireSRWLockExclusive","ReleaseSRWLockExclusive"]},{"name":"api-ms-win-core-libraryloader-l1-2-0.dll","imports":2,"functions":["FreeLibrary","LoadLibraryExW"]},{"name":"api-ms-win-core-processenvironment-l1-1-0.dll","imports":1,"functions":["ExpandEnvironmentStringsW"]},{"name":"ntdll.dll","imports":1,"functions":["WinSqmAddToStream"]},{"name":"uxtheme.dll","imports":1,"functions":["GetCurrentThemeName"]}],"ImageDLLExports":{"exports":0,"functions":[]},"ImageHashSignatures":{"md5":"5b8211194eca9875b592d150d2a02bc6","sha2":"782c3bf9906f8ce191b97d85d2168eb73f026e13447c656c9d0d58b0529f4c9f"}}