{
  "name": "directml.dll",
  "path": "\\\\?\\C:\\Windows\\SysWOW64\\directml.dll",
  "size": 869376,
  "is_64": false,
  "is_lib": true,
  "is_dotnet": true,
  "has_imports": true,
  "has_exports": true,
  "subsystem": 3,
  "subsystem_caption": "The Windows Character (Console UI) Subsystem",
  "libs": [
    "api-ms-win-core-com-l1-1-0.dll",
    "api-ms-win-core-debug-l1-1-0.dll",
    "api-ms-win-core-errorhandling-l1-1-0.dll",
    "api-ms-win-core-handle-l1-1-0.dll",
    "api-ms-win-core-heap-l1-1-0.dll",
    "api-ms-win-core-interlocked-l1-1-0.dll",
    "api-ms-win-core-libraryloader-l1-2-0.dll",
    "api-ms-win-core-libraryloader-l1-2-1.dll",
    "api-ms-win-core-localization-l1-2-0.dll",
    "api-ms-win-core-memory-l1-1-0.dll",
    "api-ms-win-core-processthreads-l1-1-0.dll",
    "api-ms-win-core-processthreads-l1-1-1.dll",
    "api-ms-win-core-profile-l1-1-0.dll",
    "api-ms-win-core-synch-l1-1-0.dll",
    "api-ms-win-core-synch-l1-2-0.dll",
    "api-ms-win-core-sysinfo-l1-1-0.dll",
    "api-ms-win-core-util-l1-1-0.dll",
    "api-ms-win-crt-heap-l1-1-0.dll",
    "api-ms-win-crt-math-l1-1-0.dll",
    "api-ms-win-crt-private-l1-1-0.dll",
    "api-ms-win-crt-runtime-l1-1-0.dll",
    "api-ms-win-crt-stdio-l1-1-0.dll",
    "api-ms-win-crt-string-l1-1-0.dll",
    "api-ms-win-eventing-provider-l1-1-0.dll",
    "cabinet.dll",
    "d3d12.dll"
  ],
  "imports": [
    {
      "lib": "api-ms-win-crt-string-l1-1-0.dll",
      "count": 1,
      "functions": [
        "memset"
      ]
    },
    {
      "lib": "api-ms-win-core-errorhandling-l1-1-0.dll",
      "count": 4,
      "functions": [
        "GetLastError",
        "SetLastError",
        "SetUnhandledExceptionFilter",
        "UnhandledExceptionFilter"
      ]
    },
    {
      "lib": "api-ms-win-core-profile-l1-1-0.dll",
      "count": 2,
      "functions": [
        "QueryPerformanceCounter",
        "QueryPerformanceFrequency"
      ]
    },
    {
      "lib": "api-ms-win-core-libraryloader-l1-2-0.dll",
      "count": 8,
      "functions": [
        "DisableThreadLibraryCalls",
        "FreeLibrary",
        "GetModuleFileNameA",
        "GetModuleHandleExW",
        "GetModuleHandleW",
        "GetProcAddress",
        "LoadResource",
        "LockResource"
      ]
    },
    {
      "lib": "api-ms-win-crt-math-l1-1-0.dll",
      "count": 2,
      "functions": [
        "ceil",
        "log2"
      ]
    },
    {
      "lib": "api-ms-win-core-memory-l1-1-0.dll",
      "count": 2,
      "functions": [
        "VirtualAlloc",
        "VirtualFree"
      ]
    },
    {
      "lib": "api-ms-win-core-com-l1-1-0.dll",
      "count": 2,
      "functions": [
        "CoTaskMemAlloc",
        "CoTaskMemFree"
      ]
    },
    {
      "lib": "api-ms-win-core-localization-l1-2-0.dll",
      "count": 1,
      "functions": [
        "FormatMessageW"
      ]
    },
    {
      "lib": "api-ms-win-core-processthreads-l1-1-1.dll",
      "count": 1,
      "functions": [
        "IsProcessorFeaturePresent"
      ]
    },
    {
      "lib": "api-ms-win-core-processthreads-l1-1-0.dll",
      "count": 4,
      "functions": [
        "GetCurrentProcess",
        "GetCurrentProcessId",
        "GetCurrentThreadId",
        "TerminateProcess"
      ]
    },
    {
      "lib": "api-ms-win-core-sysinfo-l1-1-0.dll",
      "count": 1,
      "functions": [
        "GetSystemTimeAsFileTime"
      ]
    },
    {
      "lib": "api-ms-win-core-debug-l1-1-0.dll",
      "count": 3,
      "functions": [
        "DebugBreak",
        "IsDebuggerPresent",
        "OutputDebugStringW"
      ]
    },
    {
      "lib": "api-ms-win-core-handle-l1-1-0.dll",
      "count": 1,
      "functions": [
        "CloseHandle"
      ]
    },
    {
      "lib": "api-ms-win-crt-runtime-l1-1-0.dll",
      "count": 15,
      "functions": [
        "_cexit",
        "_configure_narrow_argv",
        "_crt_atexit",
        "_errno",
        "_execute_onexit_table",
        "_initialize_narrow_environment",
        "_initialize_onexit_table",
        "_initterm",
        "_initterm_e",
        "_invalid_parameter_noinfo",
        "_invalid_parameter_noinfo_noreturn",
        "_register_onexit_function",
        "_seh_filter_dll",
        "abort",
        "terminate"
      ]
    },
    {
      "lib": "api-ms-win-core-synch-l1-1-0.dll",
      "count": 13,
      "functions": [
        "AcquireSRWLockExclusive",
        "CreateMutexExW",
        "CreateSemaphoreExW",
        "DeleteCriticalSection",
        "InitializeCriticalSectionEx",
        "InitializeSRWLock",
        "OpenSemaphoreW",
        "ReleaseMutex",
        "ReleaseSRWLockExclusive",
        "ReleaseSemaphore",
        "TryAcquireSRWLockExclusive",
        "WaitForSingleObject",
        "WaitForSingleObjectEx"
      ]
    },
    {
      "lib": "api-ms-win-crt-private-l1-1-0.dll",
      "count": 11,
      "functions": [
        "_CxxThrowException",
        "__CxxFrameHandler3",
        "__std_exception_copy",
        "__std_exception_destroy",
        "__std_terminate",
        "__std_type_info_destroy_list",
        "_except_handler4_common",
        "_purecall",
        "memcmp",
        "memcpy",
        "memmove"
      ]
    },
    {
      "lib": "api-ms-win-core-libraryloader-l1-2-1.dll",
      "count": 2,
      "functions": [
        "FindResourceW",
        "LoadLibraryW"
      ]
    },
    {
      "lib": "api-ms-win-core-heap-l1-1-0.dll",
      "count": 3,
      "functions": [
        "GetProcessHeap",
        "HeapAlloc",
        "HeapFree"
      ]
    },
    {
      "lib": "api-ms-win-core-synch-l1-2-0.dll",
      "count": 1,
      "functions": [
        "InitOnceExecuteOnce"
      ]
    },
    {
      "lib": "d3d12.dll",
      "count": 1,
      "functions": [
        "D3D12SerializeVersionedRootSignature"
      ]
    },
    {
      "lib": "api-ms-win-eventing-provider-l1-1-0.dll",
      "count": 4,
      "functions": [
        "EventRegister",
        "EventSetInformation",
        "EventUnregister",
        "EventWriteTransfer"
      ]
    },
    {
      "lib": "api-ms-win-core-util-l1-1-0.dll",
      "count": 1,
      "functions": [
        "DecodePointer"
      ]
    },
    {
      "lib": "api-ms-win-crt-heap-l1-1-0.dll",
      "count": 3,
      "functions": [
        "_callnewh",
        "free",
        "malloc"
      ]
    },
    {
      "lib": "cabinet.dll",
      "count": 3,
      "functions": [
        "ORDINAL 40",
        "ORDINAL 43",
        "ORDINAL 45"
      ]
    },
    {
      "lib": "api-ms-win-core-interlocked-l1-1-0.dll",
      "count": 1,
      "functions": [
        "InitializeSListHead"
      ]
    },
    {
      "lib": "api-ms-win-crt-stdio-l1-1-0.dll",
      "count": 3,
      "functions": [
        "__stdio_common_vsnprintf_s",
        "__stdio_common_vsprintf_s",
        "__stdio_common_vswprintf"
      ]
    }
  ],
  "exports": {
    "count": 2,
    "functions": [
      "DMLCreateDevice",
      "DMLCreateDevice1"
    ]
  },
  "hashes": {
    "sha2": "ad84c68aefe9eb5cad4c3adf9e4c0322046310b333559513dd7b8de87a854fae",
    "ssdeep": "24576:hUH4rIhv9WPVu5kFFgqBnrIsJQ+5WkwkCR8hg5jeL6NlPDLOIoh9HCGS4oknC5MH:hUH4rIhv9WPA5kFFgqZrIMcVl+hg5je9"
  },
  "intent": {
    "intentions": 1,
    "uniq_apis_matched": 1,
    "results": [
      {
        "intent": "Can Terminate Processes On The Target System",
        "tag": "Expert Input:IBO.0025",
        "component": "---",
        "inputs": 1,
        "matches": 1,
        "apis": [
          "TerminateProcess"
        ]
      }
    ]
  }
}