{
  "name": "iepeers.dll",
  "path": "\\\\?\\C:\\Windows\\WinSxS\\wow64_microsoft-windows-ie-behaviors_31bf3856ad364e35_11.0.19041.1682_none_ff6d327e0532c643\\iepeers.dll",
  "size": 160256,
  "is_64": false,
  "is_lib": true,
  "is_dotnet": true,
  "has_imports": true,
  "has_exports": true,
  "subsystem": 2,
  "subsystem_caption": "The Windows Graphical User Interface (GUI) Subsystem",
  "libs": [
    "advapi32.dll",
    "iertutil.dll",
    "kernel32.dll",
    "msvcrt.dll",
    "ole32.dll",
    "shlwapi.dll",
    "user32.dll"
  ],
  "imports": [
    {
      "lib": "kernel32.dll",
      "count": 71,
      "functions": [
        "AcquireSRWLockExclusive",
        "AcquireSRWLockShared",
        "ActivateActCtx",
        "CloseHandle",
        "CloseThreadpoolTimer",
        "CreateActCtxW",
        "CreateMutexExW",
        "CreateSemaphoreExW",
        "CreateThreadpoolTimer",
        "DeactivateActCtx",
        "DebugBreak",
        "DelayLoadFailureHook",
        "DeleteCriticalSection",
        "DisableThreadLibraryCalls",
        "EnterCriticalSection",
        "FindResourceW",
        "FormatMessageW",
        "FreeLibrary",
        "GetCurrentProcess",
        "GetCurrentProcessId",
        "GetCurrentThreadId",
        "GetDateFormatEx",
        "GetLastError",
        "GetLocalTime",
        "GetModuleFileNameA",
        "GetModuleFileNameW",
        "GetModuleHandleExW",
        "GetModuleHandleW",
        "GetProcAddress",
        "GetProcessHeap",
        "GetSystemTimeAsFileTime",
        "GetTickCount",
        "GetTimeFormatEx",
        "GetUserDefaultLCID",
        "GlobalAlloc",
        "GlobalFree",
        "HeapAlloc",
        "HeapDestroy",
        "HeapFree",
        "InitOnceExecuteOnce",
        "InitializeCriticalSection",
        "InitializeCriticalSectionEx",
        "IsDebuggerPresent",
        "LeaveCriticalSection",
        "LoadLibraryExW",
        "LoadLibraryW",
        "LoadResource",
        "MultiByteToWideChar",
        "OpenSemaphoreW",
        "OutputDebugStringW",
        "QueryPerformanceCounter",
        "ReleaseActCtx",
        "ReleaseMutex",
        "ReleaseSRWLockExclusive",
        "ReleaseSRWLockShared",
        "ReleaseSemaphore",
        "ResolveDelayLoadedAPI",
        "SetLastError",
        "SetThreadpoolTimer",
        "SetUnhandledExceptionFilter",
        "SizeofResource",
        "Sleep",
        "SleepConditionVariableSRW",
        "TerminateProcess",
        "UnhandledExceptionFilter",
        "WaitForSingleObject",
        "WaitForSingleObjectEx",
        "WaitForThreadpoolTimerCallbacks",
        "WakeAllConditionVariable",
        "lstrcmpiW",
        "lstrcpynW"
      ]
    },
    {
      "lib": "shlwapi.dll",
      "count": 3,
      "functions": [
        "ORDINAL 158",
        "ORDINAL 176",
        "ORDINAL 2"
      ]
    },
    {
      "lib": "advapi32.dll",
      "count": 9,
      "functions": [
        "RegCloseKey",
        "RegCreateKeyExW",
        "RegDeleteKeyW",
        "RegDeleteValueW",
        "RegEnumKeyExW",
        "RegOpenKeyExW",
        "RegQueryInfoKeyW",
        "RegQueryValueExW",
        "RegSetValueExW"
      ]
    },
    {
      "lib": "ole32.dll",
      "count": 7,
      "functions": [
        "CLSIDFromProgID",
        "CoCreateInstance",
        "CoTaskMemAlloc",
        "CoTaskMemFree",
        "CoTaskMemRealloc",
        "CreateBindCtx",
        "CreateStreamOnHGlobal"
      ]
    },
    {
      "lib": "iertutil.dll",
      "count": 2,
      "functions": [
        "ORDINAL 700",
        "ORDINAL 701"
      ]
    },
    {
      "lib": "msvcrt.dll",
      "count": 22,
      "functions": [
        "_XcptFilter",
        "__dllonexit",
        "_amsg_exit",
        "_callnewh",
        "_except_handler4_common",
        "_initterm",
        "_lock",
        "_ltow",
        "_onexit",
        "_purecall",
        "_unlock",
        "_vsnwprintf",
        "_wcsicmp",
        "free",
        "malloc",
        "memcpy",
        "memcpy_s",
        "memmove_s",
        "memset",
        "realloc",
        "wcschr",
        "wcstol"
      ]
    },
    {
      "lib": "user32.dll",
      "count": 3,
      "functions": [
        "CharNextW",
        "LoadStringW",
        "MessageBoxW"
      ]
    }
  ],
  "exports": {
    "count": 5,
    "functions": [
      "DllCanUnloadNow",
      "DllEnumClassObjects",
      "DllGetClassObject",
      "DllRegisterServer",
      "DllUnregisterServer"
    ]
  },
  "hashes": {
    "sha2": "bc24dc91c2a598c1f2a8f60e7470c2ab6721c61287376d0438b2dd3b28d61e32",
    "ssdeep": "3072:fxqVdPosvR8QXdPkqRgBdL0nIg+vwN0PM5f1:oVdPPxkqy50nmwNX"
  },
  "intent": {
    "intentions": 4,
    "uniq_apis_matched": 10,
    "results": [
      {
        "intent": "Can Create/Manipulate The Windows Registry",
        "tag": "Expert Input:IBO.0008 - Create/Manipulate The Windows Registry",
        "component": "Registry",
        "inputs": 33,
        "matches": 5,
        "apis": [
          "RegCreateKeyExW",
          "RegDeleteKeyW",
          "RegDeleteValueW",
          "RegOpenKeyExW",
          "RegSetValueExW"
        ]
      },
      {
        "intent": "Queries And Discovers Windows Registry Configuration Settings",
        "tag": "Discovery:T1012 - Query Registry",
        "component": "Registry",
        "inputs": 11,
        "matches": 2,
        "apis": [
          "RegQueryInfoKeyW",
          "RegQueryValueExW"
        ]
      },
      {
        "intent": "Can Delay Loading of DLLs Until Runtime/Process Execution",
        "tag": "Expert Input:IBO.0005 - Load DLL Resources With Delay During Runtime",
        "component": "---",
        "inputs": 2,
        "matches": 2,
        "apis": [
          "DelayLoadFailureHook",
          "ResolveDelayLoadedAPI"
        ]
      },
      {
        "intent": "Can Enumerate The Windows Registry",
        "tag": "Expert Input:IBO.0009 - Enumerate The Windows Registry",
        "component": "Registry",
        "inputs": 6,
        "matches": 1,
        "apis": [
          "RegEnumKeyExW"
        ]
      }
    ]
  }
}