{
  "pe_name": "iepeers.dll",
  "pe_type": 267,
  "pe_size": 160256,
  "pe_subsystem": 2,
  "pe_subsystem_caption": "The Windows graphical user interface (GUI) subsystem",
  "pe_path": "c:\\Windows\\SysWOW64\\iepeers.dll",
  "pe_timedate_stamp": 418894631,
  "pe_timedate_human": "1983-04-11T07:37:11.000Z",
  "ImageDLLImports": [
    {
      "name": "msvcrt.dll",
      "imports": 22,
      "functions": [
        "_XcptFilter",
        "__dllonexit",
        "_amsg_exit",
        "_callnewh",
        "_except_handler4_common",
        "_initterm",
        "_lock",
        "_ltow",
        "_onexit",
        "_purecall",
        "_unlock",
        "_vsnwprintf",
        "_wcsicmp",
        "free",
        "malloc",
        "memcpy",
        "memcpy_s",
        "memmove_s",
        "memset",
        "realloc",
        "wcschr",
        "wcstol"
      ]
    },
    {
      "name": "kernel32.dll",
      "imports": 71,
      "functions": [
        "AcquireSRWLockExclusive",
        "AcquireSRWLockShared",
        "ActivateActCtx",
        "CloseHandle",
        "CloseThreadpoolTimer",
        "CreateActCtxW",
        "CreateMutexExW",
        "CreateSemaphoreExW",
        "CreateThreadpoolTimer",
        "DeactivateActCtx",
        "DebugBreak",
        "DelayLoadFailureHook",
        "DeleteCriticalSection",
        "DisableThreadLibraryCalls",
        "EnterCriticalSection",
        "FindResourceW",
        "FormatMessageW",
        "FreeLibrary",
        "GetCurrentProcess",
        "GetCurrentProcessId",
        "GetCurrentThreadId",
        "GetDateFormatEx",
        "GetLastError",
        "GetLocalTime",
        "GetModuleFileNameA",
        "GetModuleFileNameW",
        "GetModuleHandleExW",
        "GetModuleHandleW",
        "GetProcAddress",
        "GetProcessHeap",
        "GetSystemTimeAsFileTime",
        "GetTickCount",
        "GetTimeFormatEx",
        "GetUserDefaultLCID",
        "GlobalAlloc",
        "GlobalFree",
        "HeapAlloc",
        "HeapDestroy",
        "HeapFree",
        "InitOnceExecuteOnce",
        "InitializeCriticalSection",
        "InitializeCriticalSectionEx",
        "IsDebuggerPresent",
        "LeaveCriticalSection",
        "LoadLibraryExW",
        "LoadLibraryW",
        "LoadResource",
        "MultiByteToWideChar",
        "OpenSemaphoreW",
        "OutputDebugStringW",
        "QueryPerformanceCounter",
        "ReleaseActCtx",
        "ReleaseMutex",
        "ReleaseSRWLockExclusive",
        "ReleaseSRWLockShared",
        "ReleaseSemaphore",
        "ResolveDelayLoadedAPI",
        "SetLastError",
        "SetThreadpoolTimer",
        "SetUnhandledExceptionFilter",
        "SizeofResource",
        "Sleep",
        "SleepConditionVariableSRW",
        "TerminateProcess",
        "UnhandledExceptionFilter",
        "WaitForSingleObject",
        "WaitForSingleObjectEx",
        "WaitForThreadpoolTimerCallbacks",
        "WakeAllConditionVariable",
        "lstrcmpiW",
        "lstrcpynW"
      ]
    },
    {
      "name": "shlwapi.dll",
      "imports": 0,
      "functions": []
    },
    {
      "name": "user32.dll",
      "imports": 2,
      "functions": [
        "CharNextW",
        "LoadStringW"
      ]
    },
    {
      "name": "ole32.dll",
      "imports": 6,
      "functions": [
        "CLSIDFromProgID",
        "CoCreateInstance",
        "CoTaskMemAlloc",
        "CoTaskMemRealloc",
        "CreateBindCtx",
        "CreateStreamOnHGlobal"
      ]
    },
    {
      "name": "advapi32.dll",
      "imports": 9,
      "functions": [
        "RegCloseKey",
        "RegCreateKeyExW",
        "RegDeleteKeyW",
        "RegDeleteValueW",
        "RegEnumKeyExW",
        "RegOpenKeyExW",
        "RegQueryInfoKeyW",
        "RegQueryValueExW",
        "RegSetValueExW"
      ]
    },
    {
      "name": "iertutil.dll",
      "imports": 0,
      "functions": []
    }
  ],
  "ImageDLLExports": {
    "exports": 5,
    "functions": [
      "DllCanUnloadNow",
      "DllEnumClassObjects",
      "DllGetClassObject",
      "DllRegisterServer",
      "DllUnregisterServer"
    ]
  },
  "ImageHashSignatures": {
    "sha2": "bc24dc91c2a598c1f2a8f60e7470c2ab6721c61287376d0438b2dd3b28d61e32"
  },
  "scan": {
    "intentions": 4,
    "uniq_apis_matched": 10,
    "results": [
      {
        "intent": "Query And Discover Windows Registry Configuration Settings",
        "tag": "Discovery:T1012 - Query Registry",
        "component": "Registry",
        "inputs": 11,
        "matches": 2,
        "apis": [
          "RegQueryInfoKeyW",
          "RegQueryValueExW"
        ]
      },
      {
        "intent": "Implements Features To Create/Manipulate The Windows Registry",
        "tag": "Expert Input:IBO.0008 - Create/Manipulate The Windows Registry",
        "component": "Registry",
        "inputs": 33,
        "matches": 5,
        "apis": [
          "RegCreateKeyExW",
          "RegDeleteKeyW",
          "RegDeleteValueW",
          "RegOpenKeyExW",
          "RegSetValueExW"
        ]
      },
      {
        "intent": "Implements Features To Enumerate The Windows Registry",
        "tag": "Expert Input:IBO.0009 - Enumerate The Windows Registry",
        "component": "Registry",
        "inputs": 6,
        "matches": 1,
        "apis": [
          "RegEnumKeyExW"
        ]
      },
      {
        "intent": "Implements Delayed Loads of DLL Resources",
        "tag": "Expert Input:IBO.0005 - Load DLL Resources With Delay During Runtime",
        "component": "---",
        "inputs": 2,
        "matches": 2,
        "apis": [
          "DelayLoadFailureHook",
          "ResolveDelayLoadedAPI"
        ]
      }
    ]
  }
}