{
  "pe_name": "iscsiexe.dll",
  "pe_type": 523,
  "pe_size": 160768,
  "pe_subsystem": 2,
  "pe_subsystem_caption": "The Windows graphical user interface (GUI) subsystem",
  "pe_path": "c:\\Windows\\WinSxS\\amd64_microsoft-windows-i..i_initiator_service_31bf3856ad364e35_10.0.19041.1766_none_4f036f27ca71d223\\iscsiexe.dll",
  "pe_timedate_stamp": 3315331739,
  "pe_timedate_human": "2075-01-21T21:28:59.000Z",
  "ImageDLLImports": [
    {
      "name": "msvcrt.dll",
      "imports": 25,
      "functions": [
        "_XcptFilter",
        "__C_specific_handler",
        "_amsg_exit",
        "_initterm",
        "_strnicmp",
        "_vsnwprintf",
        "_wcsicmp",
        "_wcsnicmp",
        "_wcsupr",
        "_wtoi",
        "atoi",
        "difftime",
        "free",
        "isdigit",
        "iswdigit",
        "malloc",
        "memcmp",
        "memcpy",
        "memset",
        "printf",
        "rand_s",
        "time",
        "wcsncmp",
        "wcsnlen",
        "wcsstr"
      ]
    },
    {
      "name": "iscsium.dll",
      "imports": 56,
      "functions": [
        "DiscpAddStringToMultiSzList",
        "DiscpAlignDataStruct",
        "DiscpAllocMemory",
        "DiscpAllocProcessMemory",
        "DiscpAnsiCharsToString",
        "DiscpAnsiToUnicode",
        "DiscpCopyString",
        "DiscpCopyToCountedString",
        "DiscpCopyUnicodeString",
        "DiscpDecryptBuffer",
        "DiscpDisableEventlog",
        "DiscpDisableWinsock",
        "DiscpDisestablishIrpPump",
        "DiscpDuplicateString",
        "DiscpEnableEventlog",
        "DiscpEnableWinsock",
        "DiscpEncryptBuffer",
        "DiscpEnumerateDeviceInterfaces",
        "DiscpEnumerateRegistryValues",
        "DiscpEstablishIrpPump",
        "DiscpEstablishTCPSocket",
        "DiscpExecuteMethod",
        "DiscpFreeDeviceInterfaceList",
        "DiscpFreeMemory",
        "DiscpFreeProcessMemory",
        "DiscpGenerateiScsiNameFromComputerName",
        "DiscpGetPnpDeviceId",
        "DiscpGetRegistryValue",
        "DiscpGetStringFromDataBlock",
        "DiscpIsDNSAddress",
        "DiscpIsStringInList",
        "DiscpLoadSystemLibrary",
        "DiscpOpenRegistryKey",
        "DiscpPadDataBlock",
        "DiscpParseAllData",
        "DiscpParseKeyValue",
        "DiscpParseSingleInstance",
        "DiscpPnpDeviceInterfaceToInstanceName",
        "DiscpQueryAllData",
        "DiscpQuerySingleInstance",
        "DiscpRegisterForDeviceInterfaceNotfication",
        "DiscpRegisterHeap",
        "DiscpRemoveStringFromMultiSzList",
        "DiscpReportEventlog",
        "DiscpReportEventlogWithStatus",
        "DiscpSendIrpRequest",
        "DiscpSetRegistryValue",
        "DiscpTextAddrToBinary",
        "DiscpULongAddList",
        "DiscpUTF8ToUnicode",
        "DiscpUnicodeToAnsi",
        "DiscpUnicodeToAnsiSize",
        "DiscpUnicodeToUTF8",
        "DiscpValidateiSCSIString",
        "DiscpXtoI",
        "Discpxtoi"
      ]
    },
    {
      "name": "ntdll.dll",
      "imports": 9,
      "functions": [
        "RtlCaptureContext",
        "RtlCreateHeap",
        "RtlDeleteCriticalSection",
        "RtlDestroyHeap",
        "RtlEnterCriticalSection",
        "RtlInitializeCriticalSection",
        "RtlLeaveCriticalSection",
        "RtlLookupFunctionEntry",
        "RtlVirtualUnwind"
      ]
    },
    {
      "name": "wmiclnt.dll",
      "imports": 4,
      "functions": [
        "WmiCloseBlock",
        "WmiFileHandleToInstanceNameW",
        "WmiNotificationRegistrationW",
        "WmiOpenBlock"
      ]
    },
    {
      "name": "rpcrt4.dll",
      "imports": 9,
      "functions": [
        "NdrServerCall2",
        "NdrServerCallAll",
        "RpcImpersonateClient",
        "RpcRevertToSelf",
        "RpcServerListen",
        "RpcServerRegisterIfEx",
        "RpcServerUnregisterIf",
        "RpcServerUseProtseqEpW",
        "UuidCreate"
      ]
    },
    {
      "name": "api-ms-win-core-registry-l1-1-0.dll",
      "imports": 7,
      "functions": [
        "RegCloseKey",
        "RegDeleteValueW",
        "RegEnumValueW",
        "RegOpenKeyExA",
        "RegQueryInfoKeyW",
        "RegQueryValueExA",
        "RegSetValueExW"
      ]
    },
    {
      "name": "api-ms-win-core-errorhandling-l1-1-0.dll",
      "imports": 4,
      "functions": [
        "GetLastError",
        "RaiseException",
        "SetUnhandledExceptionFilter",
        "UnhandledExceptionFilter"
      ]
    },
    {
      "name": "api-ms-win-service-core-l1-1-0.dll",
      "imports": 2,
      "functions": [
        "RegisterServiceCtrlHandlerExW",
        "SetServiceStatus"
      ]
    },
    {
      "name": "api-ms-win-security-base-l1-1-0.dll",
      "imports": 3,
      "functions": [
        "AllocateAndInitializeSid",
        "CheckTokenMembership",
        "FreeSid"
      ]
    },
    {
      "name": "devobj.dll",
      "imports": 10,
      "functions": [
        "DevObjChangeState",
        "DevObjCreateDeviceInfo",
        "DevObjCreateDeviceInfoList",
        "DevObjDestroyDeviceInfoList",
        "DevObjEnumDeviceInfo",
        "DevObjEnumDeviceInterfaces",
        "DevObjGetClassDevs",
        "DevObjGetDeviceInterfaceDetail",
        "DevObjRegisterDeviceInfo",
        "DevObjSetDeviceRegistryProperty"
      ]
    },
    {
      "name": "api-ms-win-service-private-l1-1-0.dll",
      "imports": 2,
      "functions": [
        "I_ScRegisterDeviceNotification",
        "I_ScUnregisterDeviceNotification"
      ]
    },
    {
      "name": "api-ms-win-devices-config-l1-1-1.dll",
      "imports": 7,
      "functions": [
        "CM_Get_Child",
        "CM_Get_DevNode_Registry_PropertyW",
        "CM_Get_Device_IDW",
        "CM_Get_Sibling",
        "CM_Locate_DevNodeW",
        "CM_Open_DevNode_Key",
        "CM_Query_And_Remove_SubTreeW"
      ]
    },
    {
      "name": "api-ms-win-core-io-l1-1-0.dll",
      "imports": 1,
      "functions": [
        "DeviceIoControl"
      ]
    },
    {
      "name": "api-ms-win-core-file-l1-1-0.dll",
      "imports": 1,
      "functions": [
        "CreateFileW"
      ]
    },
    {
      "name": "ws2_32.dll",
      "imports": 0,
      "functions": []
    },
    {
      "name": "api-ms-win-core-file-l1-2-0.dll",
      "imports": 1,
      "functions": [
        "GetVolumeNameForVolumeMountPointW"
      ]
    },
    {
      "name": "api-ms-win-core-handle-l1-1-0.dll",
      "imports": 1,
      "functions": [
        "CloseHandle"
      ]
    },
    {
      "name": "api-ms-win-core-synch-l1-1-0.dll",
      "imports": 6,
      "functions": [
        "CreateEventW",
        "CreateMutexA",
        "CreateMutexW",
        "ReleaseMutex",
        "SetEvent",
        "WaitForSingleObject"
      ]
    },
    {
      "name": "api-ms-win-core-processthreads-l1-1-0.dll",
      "imports": 5,
      "functions": [
        "CreateThread",
        "GetCurrentProcess",
        "GetCurrentProcessId",
        "GetCurrentThreadId",
        "TerminateProcess"
      ]
    },
    {
      "name": "api-ms-win-core-sysinfo-l1-1-0.dll",
      "imports": 3,
      "functions": [
        "GetComputerNameExA",
        "GetSystemTimeAsFileTime",
        "GetTickCount"
      ]
    },
    {
      "name": "api-ms-win-core-string-obsolete-l1-1-0.dll",
      "imports": 1,
      "functions": [
        "lstrcmpiW"
      ]
    },
    {
      "name": "api-ms-win-core-threadpool-legacy-l1-1-0.dll",
      "imports": 3,
      "functions": [
        "CreateTimerQueueTimer",
        "DeleteTimerQueueTimer",
        "UnregisterWaitEx"
      ]
    },
    {
      "name": "api-ms-win-core-kernel32-legacy-l1-1-0.dll",
      "imports": 1,
      "functions": [
        "RegisterWaitForSingleObject"
      ]
    },
    {
      "name": "api-ms-win-core-synch-l1-2-0.dll",
      "imports": 1,
      "functions": [
        "Sleep"
      ]
    },
    {
      "name": "api-ms-win-core-libraryloader-l1-2-0.dll",
      "imports": 1,
      "functions": [
        "FreeLibrary"
      ]
    },
    {
      "name": "iphlpapi.dll",
      "imports": 2,
      "functions": [
        "GetAdaptersInfo",
        "GetIpAddrTable"
      ]
    },
    {
      "name": "api-ms-win-core-com-l1-1-0.dll",
      "imports": 3,
      "functions": [
        "CoCreateInstance",
        "CoInitializeEx",
        "CoUninitialize"
      ]
    },
    {
      "name": "oleaut32.dll",
      "imports": 0,
      "functions": []
    },
    {
      "name": "api-ms-win-core-profile-l1-1-0.dll",
      "imports": 1,
      "functions": [
        "QueryPerformanceCounter"
      ]
    },
    {
      "name": "api-ms-win-core-synch-l1-2-1.dll",
      "imports": 1,
      "functions": [
        "WaitForMultipleObjects"
      ]
    },
    {
      "name": "api-ms-win-core-heap-l2-1-0.dll",
      "imports": 2,
      "functions": [
        "LocalAlloc",
        "LocalFree"
      ]
    },
    {
      "name": "fwpuclnt.dll",
      "imports": 11,
      "functions": [
        "FwpmEngineClose0",
        "FwpmEngineOpen0",
        "FwpmFilterAdd0",
        "FwpmFilterDeleteByKey0",
        "FwpmIPsecTunnelAdd0",
        "FwpmIPsecTunnelDeleteByKey0",
        "FwpmProviderContextAdd0",
        "FwpmProviderContextDeleteByKey0",
        "FwpmTransactionAbort0",
        "FwpmTransactionBegin0",
        "FwpmTransactionCommit0"
      ]
    }
  ],
  "ImageDLLExports": {
    "exports": 3,
    "functions": [
      "DiscpEstablishServiceLinkage",
      "ServiceMain",
      "SvchostPushServiceGlobals"
    ]
  },
  "ImageHashSignatures": {
    "sha2": "6639d02b1fed24763fcae3d8fb919de67b3639951ad49a66a804b8304137c487"
  },
  "scan": {
    "intentions": 6,
    "uniq_apis_matched": 11,
    "results": [
      {
        "intent": "Discover Network Settings On The Target System",
        "tag": "Discovery:T1016 - System Network Configuration Discovery",
        "component": "Networking",
        "inputs": 41,
        "matches": 2,
        "apis": [
          "GetAdaptersInfo",
          "GetIpAddrTable"
        ]
      },
      {
        "intent": "Implements Features To Create/Manipulate System Services",
        "tag": "Expert Input:IBO.0007 - Create/Manipulate System Services",
        "component": "Services",
        "inputs": 19,
        "matches": 2,
        "apis": [
          "RegisterServiceCtrlHandlerExW",
          "SetServiceStatus"
        ]
      },
      {
        "intent": "Implements Features To Enumerate The Windows Registry",
        "tag": "Expert Input:IBO.0009 - Enumerate The Windows Registry",
        "component": "Registry",
        "inputs": 6,
        "matches": 1,
        "apis": [
          "RegEnumValueW"
        ]
      },
      {
        "intent": "Manipulate Windows Tokens",
        "tag": "Defense Evasion:T1134 - Access Token Manipulation",
        "component": "Privileges",
        "inputs": 10,
        "matches": 1,
        "apis": [
          "CheckTokenMembership"
        ]
      },
      {
        "intent": "Query And Discover Windows Registry Configuration Settings",
        "tag": "Discovery:T1012 - Query Registry",
        "component": "Registry",
        "inputs": 11,
        "matches": 2,
        "apis": [
          "RegQueryInfoKeyW",
          "RegQueryValueExA"
        ]
      },
      {
        "intent": "Implements Features To Create/Manipulate The Windows Registry",
        "tag": "Expert Input:IBO.0008 - Create/Manipulate The Windows Registry",
        "component": "Registry",
        "inputs": 33,
        "matches": 3,
        "apis": [
          "RegDeleteValueW",
          "RegOpenKeyExA",
          "RegSetValueExW"
        ]
      }
    ]
  }
}