{
  "name": "mmcfxcommon.ni.dll",
  "path": "\\\\?\\C:\\Windows\\assembly\\NativeImages_v4.0.30319_64\\MMCFxCommon\\6f32e845e311979c3d066e5897f9af85\\MMCFxCommon.ni.dll",
  "size": 324608,
  "type": "win-pe",
  "is_64": true,
  "is_lib": true,
  "is_dotnet": false,
  "has_imports": true,
  "has_exports": false,
  "subsystem": 3,
  "subsystem_caption": "The Windows Character (Console UI) Subsystem",
  "libs": [
    ""
  ],
  "imports": [
    {
      "lib": "",
      "count": 0,
      "functions": []
    }
  ],
  "hashes": {
    "sha2": "945c9a24671015edfb29b4f10861b5fe5d839506ce77699faf3b65dcb0c981c3",
    "ssdeep": "3072:nlEZSsE29kLMisBkMYPbpuYiIRBTK7e0JYtffIjHKqWbp+FdsAKMnY0UP8FOjngS:cSs6L4IbpuYix2tnyWbgFKAKMYXtM"
  }
}