{
  "name": "mshtmled.dll",
  "path": "\\\\?\\C:\\Windows\\SysWOW64\\mshtmled.dll",
  "size": 79872,
  "is_64": false,
  "is_lib": true,
  "is_dotnet": true,
  "has_imports": true,
  "has_exports": true,
  "subsystem": 2,
  "subsystem_caption": "The Windows Graphical User Interface (GUI) Subsystem",
  "libs": [
    "advapi32.dll",
    "comdlg32.dll",
    "gdi32.dll",
    "iertutil.dll",
    "kernel32.dll",
    "msvcrt.dll",
    "ole32.dll",
    "shlwapi.dll",
    "user32.dll"
  ],
  "imports": [
    {
      "lib": "shlwapi.dll",
      "count": 4,
      "functions": [
        "ORDINAL 29",
        "StrCmpIW",
        "StrCpyNW",
        "StrStrIA"
      ]
    },
    {
      "lib": "user32.dll",
      "count": 33,
      "functions": [
        "BeginPaint",
        "CallWindowProcW",
        "CharNextW",
        "CharPrevW",
        "CreateWindowExW",
        "DefWindowProcW",
        "DestroyAcceleratorTable",
        "DestroyWindow",
        "EndPaint",
        "EqualRect",
        "GetClassInfoExW",
        "GetClientRect",
        "GetDC",
        "GetFocus",
        "GetKeyState",
        "GetKeyboardLayoutList",
        "GetSysColor",
        "GetSystemMetrics",
        "GetWindowLongW",
        "IntersectRect",
        "InvalidateRect",
        "IsChild",
        "IsWindow",
        "LoadCursorW",
        "OffsetRect",
        "RegisterClassExW",
        "ReleaseDC",
        "SetFocus",
        "SetWindowLongW",
        "SetWindowPos",
        "SetWindowRgn",
        "ShowWindow",
        "wsprintfW"
      ]
    },
    {
      "lib": "iertutil.dll",
      "count": 2,
      "functions": [
        "ORDINAL 398",
        "ORDINAL 650"
      ]
    },
    {
      "lib": "comdlg32.dll",
      "count": 3,
      "functions": [
        "ChooseColorW",
        "CommDlgExtendedError",
        "GetOpenFileNameW"
      ]
    },
    {
      "lib": "advapi32.dll",
      "count": 9,
      "functions": [
        "RegCloseKey",
        "RegCreateKeyExW",
        "RegDeleteValueW",
        "RegEnumKeyExW",
        "RegEnumValueW",
        "RegOpenKeyExW",
        "RegQueryInfoKeyW",
        "RegQueryValueExW",
        "RegSetValueExW"
      ]
    },
    {
      "lib": "msvcrt.dll",
      "count": 15,
      "functions": [
        "_XcptFilter",
        "_amsg_exit",
        "_except_handler4_common",
        "_initterm",
        "_wcsnicmp",
        "bsearch",
        "free",
        "malloc",
        "memcpy",
        "memcpy_s",
        "memset",
        "wcscat_s",
        "wcscpy_s",
        "wcsrchr",
        "wcsstr"
      ]
    },
    {
      "lib": "kernel32.dll",
      "count": 56,
      "functions": [
        "CompareStringW",
        "DecodePointer",
        "DelayLoadFailureHook",
        "DeleteCriticalSection",
        "DisableThreadLibraryCalls",
        "EncodePointer",
        "EnterCriticalSection",
        "EnumUILanguagesW",
        "FindResourceExW",
        "FlushInstructionCache",
        "FreeLibrary",
        "GetCurrentProcess",
        "GetCurrentProcessId",
        "GetCurrentThreadId",
        "GetLastError",
        "GetLocaleInfoW",
        "GetModuleFileNameA",
        "GetModuleFileNameW",
        "GetModuleHandleW",
        "GetProcAddress",
        "GetProcessHeap",
        "GetSystemInfo",
        "GetSystemTimeAsFileTime",
        "GetTickCount",
        "GetUserDefaultUILanguage",
        "GetVersion",
        "GetVersionExW",
        "HeapAlloc",
        "HeapDestroy",
        "HeapFree",
        "HeapReAlloc",
        "InitializeCriticalSection",
        "InterlockedPopEntrySList",
        "InterlockedPushEntrySList",
        "IsProcessorFeaturePresent",
        "LeaveCriticalSection",
        "LoadLibraryExA",
        "LoadLibraryExW",
        "LoadResource",
        "MulDiv",
        "MultiByteToWideChar",
        "ProcessIdToSessionId",
        "QueryPerformanceCounter",
        "RaiseException",
        "ResolveDelayLoadedAPI",
        "SetLastError",
        "SetUnhandledExceptionFilter",
        "SizeofResource",
        "Sleep",
        "TerminateProcess",
        "UnhandledExceptionFilter",
        "VirtualAlloc",
        "VirtualFree",
        "VirtualProtect",
        "VirtualQuery",
        "WTSGetActiveConsoleSessionId"
      ]
    },
    {
      "lib": "gdi32.dll",
      "count": 15,
      "functions": [
        "CreateDCW",
        "CreateFontIndirectW",
        "CreateRectRgnIndirect",
        "DeleteDC",
        "DeleteObject",
        "EnumFontFamiliesExW",
        "GetDeviceCaps",
        "GetTextCharset",
        "LPtoDP",
        "RestoreDC",
        "SaveDC",
        "SelectObject",
        "SetMapMode",
        "SetViewportOrgEx",
        "SetWindowOrgEx"
      ]
    },
    {
      "lib": "ole32.dll",
      "count": 8,
      "functions": [
        "CoCreateInstance",
        "CoTaskMemAlloc",
        "CoTaskMemFree",
        "CoTaskMemRealloc",
        "CreateOleAdviseHolder",
        "OleRegEnumVerbs",
        "OleRegGetMiscStatus",
        "OleRegGetUserType"
      ]
    }
  ],
  "exports": {
    "count": 5,
    "functions": [
      "DllCanUnloadNow",
      "DllEnumClassObjects",
      "DllGetClassObject",
      "DllRegisterServer",
      "DllUnregisterServer"
    ]
  },
  "hashes": {
    "sha2": "b1937c173563954be921222bf5109eb7c1a5012f4480329f6de85005beeb9b40",
    "ssdeep": "1536:lZ2TfNtz4mSsTSowmXIFdpMtbXfURs8tTvmyqIX:lmh4mSsTSowS8dpSfURltiypX"
  },
  "intent": {
    "intentions": 4,
    "uniq_apis_matched": 10,
    "results": [
      {
        "intent": "Can Create/Manipulate The Windows Registry",
        "tag": "Expert Input:IBO.0008 - Create/Manipulate The Windows Registry",
        "component": "Registry",
        "inputs": 33,
        "matches": 4,
        "apis": [
          "RegCreateKeyExW",
          "RegDeleteValueW",
          "RegOpenKeyExW",
          "RegSetValueExW"
        ]
      },
      {
        "intent": "Can Delay Loading of DLLs Until Runtime/Process Execution",
        "tag": "Expert Input:IBO.0005 - Load DLL Resources With Delay During Runtime",
        "component": "---",
        "inputs": 2,
        "matches": 2,
        "apis": [
          "DelayLoadFailureHook",
          "ResolveDelayLoadedAPI"
        ]
      },
      {
        "intent": "Queries And Discovers Windows Registry Configuration Settings",
        "tag": "Discovery:T1012 - Query Registry",
        "component": "Registry",
        "inputs": 11,
        "matches": 2,
        "apis": [
          "RegQueryInfoKeyW",
          "RegQueryValueExW"
        ]
      },
      {
        "intent": "Can Enumerate The Windows Registry",
        "tag": "Expert Input:IBO.0009 - Enumerate The Windows Registry",
        "component": "Registry",
        "inputs": 6,
        "matches": 2,
        "apis": [
          "RegEnumKeyExW",
          "RegEnumValueW"
        ]
      }
    ]
  }
}