{
  "name": "verclsid.exe",
  "path": "\\\\?\\C:\\Windows\\System32\\verclsid.exe",
  "size": 13824,
  "type": "win-pe",
  "is_64": true,
  "is_lib": false,
  "is_dotnet": false,
  "has_imports": true,
  "has_exports": false,
  "subsystem": 2,
  "subsystem_caption": "The Windows Graphical User Interface (GUI) Subsystem",
  "libs": [
    "kernel32.dll",
    "msvcrt.dll",
    "ole32.dll"
  ],
  "imports": [
    {
      "lib": "kernel32.dll",
      "count": 23,
      "functions": [
        "DelayLoadFailureHook",
        "ExitProcess",
        "FreeLibrary",
        "GetCommandLineW",
        "GetCurrentProcess",
        "GetCurrentProcessId",
        "GetCurrentThreadId",
        "GetModuleHandleW",
        "GetProcAddress",
        "GetStartupInfoW",
        "GetSystemTimeAsFileTime",
        "GetTickCount",
        "HeapSetInformation",
        "LoadLibraryExA",
        "QueryPerformanceCounter",
        "RtlCaptureContext",
        "RtlLookupFunctionEntry",
        "RtlVirtualUnwind",
        "SetErrorMode",
        "SetUnhandledExceptionFilter",
        "Sleep",
        "TerminateProcess",
        "UnhandledExceptionFilter"
      ]
    },
    {
      "lib": "ole32.dll",
      "count": 4,
      "functions": [
        "CoCreateInstance",
        "CoInitializeEx",
        "CoUninitialize",
        "IIDFromString"
      ]
    },
    {
      "lib": "msvcrt.dll",
      "count": 16,
      "functions": [
        "?terminate@@YAXXZ",
        "_XcptFilter",
        "__C_specific_handler",
        "__set_app_type",
        "__setusermatherr",
        "__wgetmainargs",
        "_amsg_exit",
        "_cexit",
        "_commode",
        "_exit",
        "_fmode",
        "_initterm",
        "_snwscanf_s",
        "_wcmdln",
        "exit",
        "memset"
      ]
    }
  ],
  "hashes": {
    "sha2": "ac6e1f614cb902c0abe4297646e21c70590624b652a080bfbb8407b1ab52609d",
    "ssdeep": "192:1S1rPu2/TzyyIDWm8ZdFN2y9qnWJ8VaZGuJG+WfCkXWSNW:1S17uezxm8vL2PWJqOGuUCoWSNW"
  },
  "intent": {
    "intentions": 2,
    "uniq_apis_matched": 2,
    "results": [
      {
        "intent": "Can Be Invoked With CommandLine Arguments From a Console/Terminal",
        "tag": "Expert Input:IBO.0001 - Accepts CommandLine Arguments",
        "component": "Processes",
        "inputs": 3,
        "matches": 1,
        "apis": [
          "__wgetmainargs"
        ]
      },
      {
        "intent": "Can Delay Loading of DLLs Until Runtime/Process Execution",
        "tag": "Expert Input:IBO.0005 - Load DLL Resources With Delay During Runtime",
        "component": "Memory",
        "inputs": 2,
        "matches": 1,
        "apis": [
          "DelayLoadFailureHook"
        ]
      }
    ]
  }
}